flect/__init__.py
flect/actions.py
flect/application.py
flect/config.py
flect/constants.py
flect/head.py
flect/py.typed
flect/render.py
flect/response.py
flect/sitemap.py
flect/types.py
flect/utils.py
flect/version.py
flect/component/__init__.py
flect/component/components.py
flect/component/data_grid.py
flect/component/display.py
flect/component/form.py
flect/routing/__init__.py
flect/routing/client.py
flect/routing/server.py
flect/routing/sort.py
flect-0.2.10.dist-info/METADATA
flect-0.2.10.dist-info/WHEEL
flect-0.2.10.dist-info/licenses/LICENSE
flect-0.2.10.dist-info/RECORD
