Metadata-Version: 2.3
Name: flect
Version: 0.2.10
Summary: Turning ideas into web app fast.
Project-URL: Homepage, https://github.com/Chaoyingz/flect
Project-URL: Documentation, https://flect.celerforge.com/
Project-URL: Source, https://github.com/Chaoyingz/flect
Author-email: Chaoying <chaunceywe@gmail.com>
License: MIT
License-File: LICENSE
Classifier: Development Status :: 4 - Beta
Classifier: Framework :: FastAPI
Classifier: Framework :: Pydantic :: 2
Classifier: Intended Audience :: Developers
Classifier: Intended Audience :: Information Technology
Classifier: License :: OSI Approved :: MIT License
Classifier: Programming Language :: Python :: 3
Classifier: Programming Language :: Python :: 3 :: Only
Classifier: Programming Language :: Python :: 3.9
Classifier: Programming Language :: Python :: 3.10
Classifier: Programming Language :: Python :: 3.11
Classifier: Programming Language :: Python :: 3.12
Classifier: Topic :: Internet
Requires-Python: >=3.9
Requires-Dist: fastapi>=0.108.0
Requires-Dist: pydantic>=2.6.1
Requires-Dist: pyromark>=0.3.0
Requires-Dist: uvicorn>=0.25.0
